buildapp/__init__.py
buildapp/buildapp.py
buildapp/download_tools.py
buildapp-1.5.0.dist-info/METADATA
buildapp-1.5.0.dist-info/WHEEL
buildapp-1.5.0.dist-info/entry_points.txt
buildapp-1.5.0.dist-info/top_level.txt
buildapp-1.5.0.dist-info/RECORD
