Metadata-Version: 2.4
Name: buildapp
Version: 1.5.0
Summary: Apk builder script
Home-page: https://github.com/mon231/buildapp/
Author: Ariel Tubul
Requires-Dist: requests
Dynamic: author
Dynamic: description
Dynamic: description-content-type
Dynamic: home-page
Dynamic: requires-dist
Dynamic: summary
